{
  "db_name": "MySQL",
  "query": "SELECT item_id, type as item_type, amount FROM purchase_item WHERE purchase_name = ?",
  "describe": {
    "columns": [
      {
        "ordinal": 0,
        "name": "item_id",
        "type_info": {
          "type": "VarString",
          "flags": "NOT_NULL | PRIMARY_KEY | NO_DEFAULT_VALUE",
          "char_set": 224,
          "max_size": 1020
        }
      },
      {
        "ordinal": 1,
        "name": "item_type",
        "type_info": {
          "type": "VarString",
          "flags": "NOT_NULL | PRIMARY_KEY | NO_DEFAULT_VALUE",
          "char_set": 224,
          "max_size": 1020
        }
      },
      {
        "ordinal": 2,
        "name": "amount",
        "type_info": {
          "type": "Long",
          "flags": "",
          "char_set": 63,
          "max_size": 11
        }
      }
    ],
    "parameters": {
      "Right": 1
    },
    "nullable": [
      false,
      false,
      true
    ]
  },
  "hash": "29ca4259a1b91db57748e61a03b1e479f5cec824264abd3d0a9c6618ce3ae006"
}
