{
  "db_name": "MySQL",
  "query": "SELECT user_id, password, ban_flag FROM user WHERE name = ?",
  "describe": {
    "columns": [
      {
        "ordinal": 0,
        "name": "user_id",
        "type_info": {
          "type": "Long",
          "flags": "NOT_NULL | PRIMARY_KEY | AUTO_INCREMENT",
          "char_set": 63,
          "max_size": 11
        }
      },
      {
        "ordinal": 1,
        "name": "password",
        "type_info": {
          "type": "Blob",
          "flags": "BLOB",
          "char_set": 224,
          "max_size": 262140
        }
      },
      {
        "ordinal": 2,
        "name": "ban_flag",
        "type_info": {
          "type": "Blob",
          "flags": "BLOB",
          "char_set": 224,
          "max_size": 262140
        }
      }
    ],
    "parameters": {
      "Right": 1
    },
    "nullable": [
      false,
      true,
      true
    ]
  },
  "hash": "71500ae9aaf50392088c03d81cb791ab7f9e11984ba87f3a9660373d7b79f2f8"
}
