{
  "db_name": "MySQL",
  "query": "SELECT bs.user_id, bs.song_id, bs.difficulty, bs.score, bs.shiny_perfect_count,\n             bs.perfect_count, bs.near_count, bs.miss_count, bs.health, bs.modifier,\n             bs.time_played, bs.best_clear_type, bs.clear_type, bs.rating, bs.score_v2,\n             u.name, u.character_id, u.is_char_uncapped, u.is_skill_sealed\n             FROM best_score bs\n             JOIN user u ON bs.user_id = u.user_id\n             WHERE bs.song_id = ? AND bs.difficulty = ?\n             ORDER BY bs.score DESC\n             LIMIT 20",
  "describe": {
    "columns": [
      {
        "ordinal": 0,
        "name": "user_id",
        "type_info": {
          "type": "Long",
          "flags": "NOT_NULL | PRIMARY_KEY | NO_DEFAULT_VALUE",
          "char_set": 63,
          "max_size": 11
        }
      },
      {
        "ordinal": 1,
        "name": "song_id",
        "type_info": {
          "type": "VarString",
          "flags": "NOT_NULL | PRIMARY_KEY | MULTIPLE_KEY | NO_DEFAULT_VALUE",
          "char_set": 224,
          "max_size": 1020
        }
      },
      {
        "ordinal": 2,
        "name": "difficulty",
        "type_info": {
          "type": "Long",
          "flags": "NOT_NULL | PRIMARY_KEY | NO_DEFAULT_VALUE",
          "char_set": 63,
          "max_size": 11
        }
      },
      {
        "ordinal": 3,
        "name": "score",
        "type_info": {
          "type": "Long",
          "flags": "",
          "char_set": 63,
          "max_size": 11
        }
      },
      {
        "ordinal": 4,
        "name": "shiny_perfect_count",
        "type_info": {
          "type": "Long",
          "flags": "",
          "char_set": 63,
          "max_size": 11
        }
      },
      {
        "ordinal": 5,
        "name": "perfect_count",
        "type_info": {
          "type": "Long",
          "flags": "",
          "char_set": 63,
          "max_size": 11
        }
      },
      {
        "ordinal": 6,
        "name": "near_count",
        "type_info": {
          "type": "Long",
          "flags": "",
          "char_set": 63,
          "max_size": 11
        }
      },
      {
        "ordinal": 7,
        "name": "miss_count",
        "type_info": {
          "type": "Long",
          "flags": "",
          "char_set": 63,
          "max_size": 11
        }
      },
      {
        "ordinal": 8,
        "name": "health",
        "type_info": {
          "type": "Long",
          "flags": "",
          "char_set": 63,
          "max_size": 11
        }
      },
      {
        "ordinal": 9,
        "name": "modifier",
        "type_info": {
          "type": "Long",
          "flags": "",
          "char_set": 63,
          "max_size": 11
        }
      },
      {
        "ordinal": 10,
        "name": "time_played",
        "type_info": {
          "type": "LongLong",
          "flags": "",
          "char_set": 63,
          "max_size": 20
        }
      },
      {
        "ordinal": 11,
        "name": "best_clear_type",
        "type_info": {
          "type": "Long",
          "flags": "",
          "char_set": 63,
          "max_size": 11
        }
      },
      {
        "ordinal": 12,
        "name": "clear_type",
        "type_info": {
          "type": "Long",
          "flags": "",
          "char_set": 63,
          "max_size": 11
        }
      },
      {
        "ordinal": 13,
        "name": "rating",
        "type_info": {
          "type": "Double",
          "flags": "",
          "char_set": 63,
          "max_size": 22
        }
      },
      {
        "ordinal": 14,
        "name": "score_v2",
        "type_info": {
          "type": "Double",
          "flags": "",
          "char_set": 63,
          "max_size": 22
        }
      },
      {
        "ordinal": 15,
        "name": "name",
        "type_info": {
          "type": "VarString",
          "flags": "UNIQUE_KEY",
          "char_set": 224,
          "max_size": 1020
        }
      },
      {
        "ordinal": 16,
        "name": "character_id",
        "type_info": {
          "type": "Long",
          "flags": "",
          "char_set": 63,
          "max_size": 11
        }
      },
      {
        "ordinal": 17,
        "name": "is_char_uncapped",
        "type_info": {
          "type": "Tiny",
          "flags": "",
          "char_set": 63,
          "max_size": 4
        }
      },
      {
        "ordinal": 18,
        "name": "is_skill_sealed",
        "type_info": {
          "type": "Tiny",
          "flags": "",
          "char_set": 63,
          "max_size": 4
        }
      }
    ],
    "parameters": {
      "Right": 2
    },
    "nullable": [
      false,
      false,
      false,
      true,
      true,
      true,
      true,
      true,
      true,
      true,
      true,
      true,
      true,
      true,
      true,
      true,
      true,
      true,
      true
    ]
  },
  "hash": "8e88449f5d9af405e7cf01ff35b38a9bb6ebbf8b5ae39f5f24d614d9f8d9107e"
}
