{
  "db_name": "MySQL",
  "query": "SELECT COUNT(*) as total FROM best_score WHERE song_id = ? AND difficulty = ?",
  "describe": {
    "columns": [
      {
        "ordinal": 0,
        "name": "total",
        "type_info": {
          "type": "LongLong",
          "flags": "NOT_NULL | BINARY",
          "char_set": 63,
          "max_size": 21
        }
      }
    ],
    "parameters": {
      "Right": 2
    },
    "nullable": [
      false
    ]
  },
  "hash": "f2460cfd94eb32bded256b22bb772a69e38302cb6af32a2636b74659527f1a7f"
}
